{
    "name": "Medico",
    "fields": [
        {
            "fieldName": "nome",
            "fieldType": "String"
        },
        {
            "fieldName": "telefone",
            "fieldType": "String"
        },
        {
            "fieldName": "email",
            "fieldType": "String"
        }
    ],
    "relationships": [
        {
            "relationshipType": "many-to-one",
            "otherEntityName": "especialidade",
            "otherEntityRelationshipName": "medico",
            "relationshipName": "especialidade",
            "otherEntityField": "id"
        }
    ],
    "changelogDate": "20200106110007",
    "entityTableName": "medico",
    "dto": "no",
    "pagination": "no",
    "service": "no",
    "jpaMetamodelFiltering": false,
    "fluentMethods": true,
    "readOnly": false,
    "clientRootFolder": "",
    "applications": "*"
}